setup.cfg
setup.py
norad/__init__.py
norad/api.py
norad/models.py
norad.egg-info/PKG-INFO
norad.egg-info/SOURCES.txt
norad.egg-info/dependency_links.txt
norad.egg-info/requires.txt
norad.egg-info/top_level.txt