Metadata-Version: 1.0
Name: norad
Version: 0.0.1
Summary: Python SDK for Norad
Home-page: https://norad-gitlab.cisco.com/norad/python-sdk/
Author: David Wyde
Author-email: dwyde@cisco.com
License: UNKNOWN
Platform: UNKNOWN
